Quickdata/Funciones.py
Quickdata/__init__.py
Quickdata-1.0.2.dist-info/METADATA
Quickdata-1.0.2.dist-info/WHEEL
Quickdata-1.0.2.dist-info/top_level.txt
Quickdata-1.0.2.dist-info/RECORD
