Metadata-Version: 2.1
Name: Quickdata
Version: 1.0.2
Summary: Automatizar labores presentes en el día a día de los Data Scientists.
Home-page: https://github.com/Diegoramirez1999/Quickdata
Author: Diego Alejandro Ramírez Araujo
Author-email: daramireza11@gmail.com
License: MIT
